gwsamplefind/__init__.py
gwsamplefind/__main__.py
gwsamplefind/client.py
gwsamplefind/exceptions.py
gwsamplefind-0.1.0.dist-info/METADATA
gwsamplefind-0.1.0.dist-info/WHEEL
gwsamplefind-0.1.0.dist-info/entry_points.txt
gwsamplefind-0.1.0.dist-info/top_level.txt
gwsamplefind-0.1.0.dist-info/RECORD
