Metadata-Version: 2.4
Name: gwsamplefind
Version: 0.1.0
Summary: Access gravitational-wave sample data
Requires-Dist: gwosc
Requires-Dist: pandas
Requires-Dist: requests
Provides-Extra: test
Requires-Dist: pytest; extra == "test"
